TSIClient/TSIClient.py
TSIClient/__init__.py
TSIClient/exceptions.py
TSIClient/authorization/__init__.py
TSIClient/authorization/authorization_api.py
TSIClient/common/__init__.py
TSIClient/common/common_funcs.py
TSIClient/environment/__init__.py
TSIClient/environment/environment_api.py
TSIClient/hierarchies/__init__.py
TSIClient/hierarchies/hierarchies_api.py
TSIClient/instances/__init__.py
TSIClient/instances/instances_api.py
TSIClient/query/__init__.py
TSIClient/query/query_api.py
TSIClient/types/__init__.py
TSIClient/types/types_api.py
tests/__init__.py
tests/conftest.py
tests/mock_responses.py
tests/test_tsiclient.py
TSIClient-2.1.3.dist-info/LICENSE.txt
TSIClient-2.1.3.dist-info/METADATA
TSIClient-2.1.3.dist-info/WHEEL
TSIClient-2.1.3.dist-info/top_level.txt
TSIClient-2.1.3.dist-info/RECORD
